omp4py/__init__.py
omp4py/api.py
omp4py/context.py
omp4py/core.py
omp4py/directives/__init__.py
omp4py/directives/atomic.py
omp4py/directives/barrier.py
omp4py/directives/clauses/__init__.py
omp4py/directives/clauses/collapse.py
omp4py/directives/clauses/copyin.py
omp4py/directives/clauses/copyprivate.py
omp4py/directives/clauses/default.py
omp4py/directives/clauses/firstprivate.py
omp4py/directives/clauses/if_.py
omp4py/directives/clauses/lastprivate.py
omp4py/directives/clauses/nowait.py
omp4py/directives/clauses/num_threads.py
omp4py/directives/clauses/ordered.py
omp4py/directives/clauses/private.py
omp4py/directives/clauses/reduction.py
omp4py/directives/clauses/schedule.py
omp4py/directives/clauses/shared.py
omp4py/directives/clauses/untied.py
omp4py/directives/critical.py
omp4py/directives/flush.py
omp4py/directives/for_.py
omp4py/directives/master.py
omp4py/directives/ordered.py
omp4py/directives/parallel.py
omp4py/directives/section.py
omp4py/directives/sections.py
omp4py/directives/single.py
omp4py/directives/task.py
omp4py/directives/taskwait.py
omp4py/directives/threadprivate.py
omp4py/error.py
omp4py/runtime.py
omp4py-0.1.dist-info/LICENSE
omp4py-0.1.dist-info/METADATA
omp4py-0.1.dist-info/WHEEL
omp4py-0.1.dist-info/RECORD
