Metadata-Version: 2.1
Name: omp4py
Version: 0.1
Summary: An OpenMP Implementation for Python
Home-page: https://github.com/citiususc/omp4py
License: LGPL-3.0-only
Keywords: HPC,OpenMP,Programming models
Author: César Pomar
Author-email: cesaralfredo.pineiro@usc.es
Requires-Python: >=3.10,<4.0
Classifier: License :: OSI Approved :: GNU Lesser General Public License v3 (LGPLv3)
Classifier: Programming Language :: Python :: 3
Classifier: Programming Language :: Python :: 3.10
Classifier: Programming Language :: Python :: 3.11
Classifier: Programming Language :: Python :: 3.12
Project-URL: Repository, https://github.com/citiususc/omp4py
